cyberfusion/RBLChecker/CLI.py
cyberfusion/RBLChecker/__init__.py
cyberfusion/RBLChecker/checkers.py
cyberfusion/RBLChecker/config.py
cyberfusion/RBLChecker/utilities.py
rblchecker-1.0.5.1.dist-info/METADATA
rblchecker-1.0.5.1.dist-info/WHEEL
rblchecker-1.0.5.1.dist-info/entry_points.txt
rblchecker-1.0.5.1.dist-info/top_level.txt
rblchecker-1.0.5.1.dist-info/RECORD
