Metadata-Version: 2.1
Name: rblchecker
Version: 1.0.5.1
Summary: Use rblchecker to check whether your outgoing mail IP addresses are listed on RBLs.
Author-email: Cyberfusion <support@cyberfusion.io>
Project-URL: Source, https://github.com/CyberfusionIO/rblchecker
Requires-Dist: docopt ==0.6.2
Requires-Dist: schema ==0.7.7
Requires-Dist: requests ==2.32.3
Requires-Dist: netaddr ==1.3.0
Requires-Dist: dnspython ==2.6.1
Requires-Dist: PyYAML ==6.0.2
